Metadata-Version: 1.1
Name: ren-salesforce-reporting
Version: 0.1.3
Summary: Get data from Salesforce reports with python
Home-page: https://github.com/renyuku/salesforce-reporting
Author: Ren Ku
Author-email: raikoo31@gmail.com
License: UNKNOWN
Keywords: python,salesforce,salesforce.com
Platform: UNKNOWN
Classifier: Programming Language :: Python :: 2
Classifier: Programming Language :: Python :: 3
